package/__init__.py
package/modul1.py
package/modul2.py
etpyfi_test-0.0.1.dist-info/METADATA
etpyfi_test-0.0.1.dist-info/WHEEL
etpyfi_test-0.0.1.dist-info/top_level.txt
etpyfi_test-0.0.1.dist-info/RECORD
