Metadata-Version: 2.1
Name: etpyfi-test
Version: 0.0.1
Summary: Eine Demonstration...
Home-page: UNKNOWN
Author: Thomas Benkenstein
Author-email: thomas.benkenstein@experteach.de
License: UNKNOWN
Keywords: python,code
Platform: UNKNOWN
Classifier: Development Status :: 1 - Planning
Classifier: Intended Audience :: Developers
Classifier: Programming Language :: Python :: 3.10
Requires-Dist: numpy (>=1.0.0)
Requires-Dist: pandas
